cmd_queue/__init__.py
cmd_queue/__main__.py
cmd_queue/__main__.pyi
cmd_queue/airflow_queue.py
cmd_queue/airflow_queue.pyi
cmd_queue/base_queue.py
cmd_queue/base_queue.pyi
cmd_queue/cli_boilerplate.py
cmd_queue/cli_boilerplate.pyi
cmd_queue/main.py
cmd_queue/main.pyi
cmd_queue/monitor_app.py
cmd_queue/monitor_app.pyi
cmd_queue/py.typed
cmd_queue/serial_queue.py
cmd_queue/serial_queue.pyi
cmd_queue/slurm_queue.py
cmd_queue/slurm_queue.pyi
cmd_queue/slurmify.py
cmd_queue/tmux_queue.py
cmd_queue/tmux_queue.pyi
cmd_queue/util/__init__.py
cmd_queue/util/richer.py
cmd_queue/util/richer.pyi
cmd_queue/util/texter.py
cmd_queue/util/texter.pyi
cmd_queue/util/textual_extensions.py
cmd_queue/util/textual_extensions.pyi
cmd_queue/util/util_algo.py
cmd_queue/util/util_algo.pyi
cmd_queue/util/util_bash.py
cmd_queue/util/util_network_text.py
cmd_queue/util/util_network_text.pyi
cmd_queue/util/util_networkx.py
cmd_queue/util/util_networkx.pyi
cmd_queue/util/util_tags.py
cmd_queue/util/util_tags.pyi
cmd_queue/util/util_tmux.py
cmd_queue/util/util_tmux.pyi
cmd_queue/util/util_yaml.py
cmd_queue/util/util_yaml.pyi
cmd_queue-0.2.2.dist-info/LICENSE
cmd_queue-0.2.2.dist-info/METADATA
cmd_queue-0.2.2.dist-info/WHEEL
cmd_queue-0.2.2.dist-info/entry_points.txt
cmd_queue-0.2.2.dist-info/top_level.txt
cmd_queue-0.2.2.dist-info/RECORD
