Metadata-Version: 2.2
Name: cmd_queue
Version: 0.2.2
Summary: The cmd_queue module for a DAG of bash commands
Home-page: https://gitlab.kitware.com/computer-vision/cmd_queue
Author: Kitware Inc., Jon Crall
Author-email: kitware@kitware.com, jon.crall@kitware.com
License: Apache 2
Classifier: Development Status :: 4 - Beta
Classifier: Intended Audience :: Developers
Classifier: Topic :: Software Development :: Libraries :: Python Modules
Classifier: Topic :: Utilities
Classifier: License :: OSI Approved :: Apache Software License
Classifier: Programming Language :: Python :: 3.8
Classifier: Programming Language :: Python :: 3.9
Classifier: Programming Language :: Python :: 3.10
Classifier: Programming Language :: Python :: 3.11
Classifier: Programming Language :: Python :: 3.12
Classifier: Programming Language :: Python :: 3.13
Requires-Python: >=3.8
License-File: LICENSE
Requires-Dist: numpy>=2.1.0; python_version < "4.0" and python_version >= "3.13"
Requires-Dist: numpy>=1.26.0; python_version < "3.13" and python_version >= "3.12"
Requires-Dist: numpy>=1.23.2; python_version < "3.12" and python_version >= "3.11"
Requires-Dist: numpy>=1.21.6; python_version < "3.11" and python_version >= "3.10"
Requires-Dist: numpy>=1.19.3; python_version < "3.10" and python_version >= "3.6.0"
Requires-Dist: ubelt>=1.3.0
Requires-Dist: networkx>=2.8; python_version < "4.0" and python_version >= "3.11"
Requires-Dist: networkx>=2.7; python_version < "3.11" and python_version >= "3.8"
Requires-Dist: networkx>=2.6.2; python_version < "3.8" and python_version >= "3.7"
Requires-Dist: networkx<=2.5.1,>=2.5.1; python_version < "3.7.0" and python_version >= "3.6.0"
Requires-Dist: rich>=12.5.1
Requires-Dist: pandas>=2.2.3; python_version < "4.0" and python_version >= "3.13"
Requires-Dist: pandas>=2.1.1; python_version < "3.13" and python_version >= "3.12"
Requires-Dist: pandas>=1.5.0; python_version < "3.12" and python_version >= "3.11"
Requires-Dist: pandas>=1.4.0; python_version < "3.11" and python_version >= "3.10"
Requires-Dist: pandas>=1.4.0; python_version < "3.10" and python_version >= "3.9"
Requires-Dist: pandas>=1.4.0; python_version < "3.9" and python_version >= "3.8"
Requires-Dist: pandas>=1.3.5; python_version < "3.8" and python_version >= "3.7"
Requires-Dist: pandas>=1.1.5; python_version < "3.7" and python_version >= "3.6"
Requires-Dist: scriptconfig>=0.7.9
Requires-Dist: psutil>=5.9.1
Requires-Dist: ruamel.yaml>=0.17.22
Provides-Extra: all
Requires-Dist: numpy>=2.1.0; (python_version < "4.0" and python_version >= "3.13") and extra == "all"
Requires-Dist: numpy>=1.26.0; (python_version < "3.13" and python_version >= "3.12") and extra == "all"
Requires-Dist: numpy>=1.23.2; (python_version < "3.12" and python_version >= "3.11") and extra == "all"
Requires-Dist: numpy>=1.21.6; (python_version < "3.11" and python_version >= "3.10") and extra == "all"
Requires-Dist: numpy>=1.19.3; (python_version < "3.10" and python_version >= "3.6.0") and extra == "all"
Requires-Dist: ubelt>=1.3.0; extra == "all"
Requires-Dist: networkx>=2.8; (python_version < "4.0" and python_version >= "3.11") and extra == "all"
Requires-Dist: networkx>=2.7; (python_version < "3.11" and python_version >= "3.8") and extra == "all"
Requires-Dist: networkx>=2.6.2; (python_version < "3.8" and python_version >= "3.7") and extra == "all"
Requires-Dist: networkx<=2.5.1,>=2.5.1; (python_version < "3.7.0" and python_version >= "3.6.0") and extra == "all"
Requires-Dist: rich>=12.5.1; extra == "all"
Requires-Dist: pandas>=2.2.3; (python_version < "4.0" and python_version >= "3.13") and extra == "all"
Requires-Dist: pandas>=2.1.1; (python_version < "3.13" and python_version >= "3.12") and extra == "all"
Requires-Dist: pandas>=1.5.0; (python_version < "3.12" and python_version >= "3.11") and extra == "all"
Requires-Dist: pandas>=1.4.0; (python_version < "3.11" and python_version >= "3.10") and extra == "all"
Requires-Dist: pandas>=1.4.0; (python_version < "3.10" and python_version >= "3.9") and extra == "all"
Requires-Dist: pandas>=1.4.0; (python_version < "3.9" and python_version >= "3.8") and extra == "all"
Requires-Dist: pandas>=1.3.5; (python_version < "3.8" and python_version >= "3.7") and extra == "all"
Requires-Dist: pandas>=1.1.5; (python_version < "3.7" and python_version >= "3.6") and extra == "all"
Requires-Dist: scriptconfig>=0.7.9; extra == "all"
Requires-Dist: psutil>=5.9.1; extra == "all"
Requires-Dist: ruamel.yaml>=0.17.22; extra == "all"
Requires-Dist: pytest>=7.1.0; python_version >= "3.7" and extra == "all"
Requires-Dist: pytest>=6.2.0; (python_version < "3.7" and python_version >= "3.6") and extra == "all"
Requires-Dist: xdoctest>=1.0.1; extra == "all"
Requires-Dist: pytest-cov>=3.0.0; python_version >= "3.6.0" and extra == "all"
Requires-Dist: coverage>=6.1.1; python_version >= "3.10" and extra == "all"
Requires-Dist: coverage>=5.3.1; (python_version < "3.10" and python_version >= "3.9") and extra == "all"
Requires-Dist: coverage>=6.1.1; (python_version < "3.9" and python_version >= "3.8") and extra == "all"
Requires-Dist: coverage>=6.1.1; (python_version < "3.8" and python_version >= "3.7") and extra == "all"
Requires-Dist: coverage>=6.1.1; (python_version < "3.7" and python_version >= "3.6") and extra == "all"
Requires-Dist: textual>=0.1.18; python_version >= "3.7" and extra == "all"
Requires-Dist: pint>=0.24.4; (python_version < "4.0" and python_version >= "3.13") and extra == "all"
Requires-Dist: pint>=0.23; (python_version < "3.13" and python_version >= "3.12") and extra == "all"
Requires-Dist: pint>=0.18; (python_version < "3.12" and python_version >= "3.11") and extra == "all"
Requires-Dist: pint>=0.18; (python_version < "3.11" and python_version >= "3.10") and extra == "all"
Requires-Dist: pint>=0.18; (python_version < "3.10" and python_version >= "3.9") and extra == "all"
Requires-Dist: pint>=0.18; (python_version < "3.9" and python_version >= "3.8") and extra == "all"
Provides-Extra: runtime
Requires-Dist: numpy>=2.1.0; (python_version < "4.0" and python_version >= "3.13") and extra == "runtime"
Requires-Dist: numpy>=1.26.0; (python_version < "3.13" and python_version >= "3.12") and extra == "runtime"
Requires-Dist: numpy>=1.23.2; (python_version < "3.12" and python_version >= "3.11") and extra == "runtime"
Requires-Dist: numpy>=1.21.6; (python_version < "3.11" and python_version >= "3.10") and extra == "runtime"
Requires-Dist: numpy>=1.19.3; (python_version < "3.10" and python_version >= "3.6.0") and extra == "runtime"
Requires-Dist: ubelt>=1.3.0; extra == "runtime"
Requires-Dist: networkx>=2.8; (python_version < "4.0" and python_version >= "3.11") and extra == "runtime"
Requires-Dist: networkx>=2.7; (python_version < "3.11" and python_version >= "3.8") and extra == "runtime"
Requires-Dist: networkx>=2.6.2; (python_version < "3.8" and python_version >= "3.7") and extra == "runtime"
Requires-Dist: networkx<=2.5.1,>=2.5.1; (python_version < "3.7.0" and python_version >= "3.6.0") and extra == "runtime"
Requires-Dist: rich>=12.5.1; extra == "runtime"
Requires-Dist: pandas>=2.2.3; (python_version < "4.0" and python_version >= "3.13") and extra == "runtime"
Requires-Dist: pandas>=2.1.1; (python_version < "3.13" and python_version >= "3.12") and extra == "runtime"
Requires-Dist: pandas>=1.5.0; (python_version < "3.12" and python_version >= "3.11") and extra == "runtime"
Requires-Dist: pandas>=1.4.0; (python_version < "3.11" and python_version >= "3.10") and extra == "runtime"
Requires-Dist: pandas>=1.4.0; (python_version < "3.10" and python_version >= "3.9") and extra == "runtime"
Requires-Dist: pandas>=1.4.0; (python_version < "3.9" and python_version >= "3.8") and extra == "runtime"
Requires-Dist: pandas>=1.3.5; (python_version < "3.8" and python_version >= "3.7") and extra == "runtime"
Requires-Dist: pandas>=1.1.5; (python_version < "3.7" and python_version >= "3.6") and extra == "runtime"
Requires-Dist: scriptconfig>=0.7.9; extra == "runtime"
Requires-Dist: psutil>=5.9.1; extra == "runtime"
Requires-Dist: ruamel.yaml>=0.17.22; extra == "runtime"
Provides-Extra: tests
Requires-Dist: pytest>=7.1.0; python_version >= "3.7" and extra == "tests"
Requires-Dist: pytest>=6.2.0; (python_version < "3.7" and python_version >= "3.6") and extra == "tests"
Requires-Dist: xdoctest>=1.0.1; extra == "tests"
Requires-Dist: pytest-cov>=3.0.0; python_version >= "3.6.0" and extra == "tests"
Requires-Dist: coverage>=6.1.1; python_version >= "3.10" and extra == "tests"
Requires-Dist: coverage>=5.3.1; (python_version < "3.10" and python_version >= "3.9") and extra == "tests"
Requires-Dist: coverage>=6.1.1; (python_version < "3.9" and python_version >= "3.8") and extra == "tests"
Requires-Dist: coverage>=6.1.1; (python_version < "3.8" and python_version >= "3.7") and extra == "tests"
Requires-Dist: coverage>=6.1.1; (python_version < "3.7" and python_version >= "3.6") and extra == "tests"
Provides-Extra: optional
Requires-Dist: textual>=0.1.18; python_version >= "3.7" and extra == "optional"
Requires-Dist: pint>=0.24.4; (python_version < "4.0" and python_version >= "3.13") and extra == "optional"
Requires-Dist: pint>=0.23; (python_version < "3.13" and python_version >= "3.12") and extra == "optional"
Requires-Dist: pint>=0.18; (python_version < "3.12" and python_version >= "3.11") and extra == "optional"
Requires-Dist: pint>=0.18; (python_version < "3.11" and python_version >= "3.10") and extra == "optional"
Requires-Dist: pint>=0.18; (python_version < "3.10" and python_version >= "3.9") and extra == "optional"
Requires-Dist: pint>=0.18; (python_version < "3.9" and python_version >= "3.8") and extra == "optional"
Provides-Extra: docs
Requires-Dist: sphinx>=5.0.1; extra == "docs"
Requires-Dist: sphinx-autobuild>=2021.3.14; extra == "docs"
Requires-Dist: sphinx_rtd_theme>=1.0.0; extra == "docs"
Requires-Dist: sphinxcontrib-napoleon>=0.7; extra == "docs"
Requires-Dist: sphinx-autoapi>=1.8.4; extra == "docs"
Requires-Dist: Pygments>=2.9.0; extra == "docs"
Requires-Dist: myst_parser>=0.18.0; extra == "docs"
Requires-Dist: sphinx-reredirects>=0.0.1; extra == "docs"
Provides-Extra: linting
Requires-Dist: flake8>=5.0.0; extra == "linting"
Provides-Extra: all-strict
Requires-Dist: numpy==2.1.0; (python_version < "4.0" and python_version >= "3.13") and extra == "all-strict"
Requires-Dist: numpy==1.26.0; (python_version < "3.13" and python_version >= "3.12") and extra == "all-strict"
Requires-Dist: numpy==1.23.2; (python_version < "3.12" and python_version >= "3.11") and extra == "all-strict"
Requires-Dist: numpy==1.21.6; (python_version < "3.11" and python_version >= "3.10") and extra == "all-strict"
Requires-Dist: numpy==1.19.3; (python_version < "3.10" and python_version >= "3.6.0") and extra == "all-strict"
Requires-Dist: ubelt==1.3.0; extra == "all-strict"
Requires-Dist: networkx==2.8; (python_version < "4.0" and python_version >= "3.11") and extra == "all-strict"
Requires-Dist: networkx==2.7; (python_version < "3.11" and python_version >= "3.8") and extra == "all-strict"
Requires-Dist: networkx==2.6.2; (python_version < "3.8" and python_version >= "3.7") and extra == "all-strict"
Requires-Dist: networkx<=2.5.1,==2.5.1; (python_version < "3.7.0" and python_version >= "3.6.0") and extra == "all-strict"
Requires-Dist: rich==12.5.1; extra == "all-strict"
Requires-Dist: pandas==2.2.3; (python_version < "4.0" and python_version >= "3.13") and extra == "all-strict"
Requires-Dist: pandas==2.1.1; (python_version < "3.13" and python_version >= "3.12") and extra == "all-strict"
Requires-Dist: pandas==1.5.0; (python_version < "3.12" and python_version >= "3.11") and extra == "all-strict"
Requires-Dist: pandas==1.4.0; (python_version < "3.11" and python_version >= "3.10") and extra == "all-strict"
Requires-Dist: pandas==1.4.0; (python_version < "3.10" and python_version >= "3.9") and extra == "all-strict"
Requires-Dist: pandas==1.4.0; (python_version < "3.9" and python_version >= "3.8") and extra == "all-strict"
Requires-Dist: pandas==1.3.5; (python_version < "3.8" and python_version >= "3.7") and extra == "all-strict"
Requires-Dist: pandas==1.1.5; (python_version < "3.7" and python_version >= "3.6") and extra == "all-strict"
Requires-Dist: scriptconfig==0.7.9; extra == "all-strict"
Requires-Dist: psutil==5.9.1; extra == "all-strict"
Requires-Dist: ruamel.yaml==0.17.22; extra == "all-strict"
Requires-Dist: pytest==7.1.0; python_version >= "3.7" and extra == "all-strict"
Requires-Dist: pytest==6.2.0; (python_version < "3.7" and python_version >= "3.6") and extra == "all-strict"
Requires-Dist: xdoctest==1.0.1; extra == "all-strict"
Requires-Dist: pytest-cov==3.0.0; python_version >= "3.6.0" and extra == "all-strict"
Requires-Dist: coverage==6.1.1; python_version >= "3.10" and extra == "all-strict"
Requires-Dist: coverage==5.3.1; (python_version < "3.10" and python_version >= "3.9") and extra == "all-strict"
Requires-Dist: coverage==6.1.1; (python_version < "3.9" and python_version >= "3.8") and extra == "all-strict"
Requires-Dist: coverage==6.1.1; (python_version < "3.8" and python_version >= "3.7") and extra == "all-strict"
Requires-Dist: coverage==6.1.1; (python_version < "3.7" and python_version >= "3.6") and extra == "all-strict"
Requires-Dist: textual==0.1.18; python_version >= "3.7" and extra == "all-strict"
Requires-Dist: pint==0.24.4; (python_version < "4.0" and python_version >= "3.13") and extra == "all-strict"
Requires-Dist: pint==0.23; (python_version < "3.13" and python_version >= "3.12") and extra == "all-strict"
Requires-Dist: pint==0.18; (python_version < "3.12" and python_version >= "3.11") and extra == "all-strict"
Requires-Dist: pint==0.18; (python_version < "3.11" and python_version >= "3.10") and extra == "all-strict"
Requires-Dist: pint==0.18; (python_version < "3.10" and python_version >= "3.9") and extra == "all-strict"
Requires-Dist: pint==0.18; (python_version < "3.9" and python_version >= "3.8") and extra == "all-strict"
Provides-Extra: runtime-strict
Requires-Dist: numpy==2.1.0; (python_version < "4.0" and python_version >= "3.13") and extra == "runtime-strict"
Requires-Dist: numpy==1.26.0; (python_version < "3.13" and python_version >= "3.12") and extra == "runtime-strict"
Requires-Dist: numpy==1.23.2; (python_version < "3.12" and python_version >= "3.11") and extra == "runtime-strict"
Requires-Dist: numpy==1.21.6; (python_version < "3.11" and python_version >= "3.10") and extra == "runtime-strict"
Requires-Dist: numpy==1.19.3; (python_version < "3.10" and python_version >= "3.6.0") and extra == "runtime-strict"
Requires-Dist: ubelt==1.3.0; extra == "runtime-strict"
Requires-Dist: networkx==2.8; (python_version < "4.0" and python_version >= "3.11") and extra == "runtime-strict"
Requires-Dist: networkx==2.7; (python_version < "3.11" and python_version >= "3.8") and extra == "runtime-strict"
Requires-Dist: networkx==2.6.2; (python_version < "3.8" and python_version >= "3.7") and extra == "runtime-strict"
Requires-Dist: networkx<=2.5.1,==2.5.1; (python_version < "3.7.0" and python_version >= "3.6.0") and extra == "runtime-strict"
Requires-Dist: rich==12.5.1; extra == "runtime-strict"
Requires-Dist: pandas==2.2.3; (python_version < "4.0" and python_version >= "3.13") and extra == "runtime-strict"
Requires-Dist: pandas==2.1.1; (python_version < "3.13" and python_version >= "3.12") and extra == "runtime-strict"
Requires-Dist: pandas==1.5.0; (python_version < "3.12" and python_version >= "3.11") and extra == "runtime-strict"
Requires-Dist: pandas==1.4.0; (python_version < "3.11" and python_version >= "3.10") and extra == "runtime-strict"
Requires-Dist: pandas==1.4.0; (python_version < "3.10" and python_version >= "3.9") and extra == "runtime-strict"
Requires-Dist: pandas==1.4.0; (python_version < "3.9" and python_version >= "3.8") and extra == "runtime-strict"
Requires-Dist: pandas==1.3.5; (python_version < "3.8" and python_version >= "3.7") and extra == "runtime-strict"
Requires-Dist: pandas==1.1.5; (python_version < "3.7" and python_version >= "3.6") and extra == "runtime-strict"
Requires-Dist: scriptconfig==0.7.9; extra == "runtime-strict"
Requires-Dist: psutil==5.9.1; extra == "runtime-strict"
Requires-Dist: ruamel.yaml==0.17.22; extra == "runtime-strict"
Provides-Extra: tests-strict
Requires-Dist: pytest==7.1.0; python_version >= "3.7" and extra == "tests-strict"
Requires-Dist: pytest==6.2.0; (python_version < "3.7" and python_version >= "3.6") and extra == "tests-strict"
Requires-Dist: xdoctest==1.0.1; extra == "tests-strict"
Requires-Dist: pytest-cov==3.0.0; python_version >= "3.6.0" and extra == "tests-strict"
Requires-Dist: coverage==6.1.1; python_version >= "3.10" and extra == "tests-strict"
Requires-Dist: coverage==5.3.1; (python_version < "3.10" and python_version >= "3.9") and extra == "tests-strict"
Requires-Dist: coverage==6.1.1; (python_version < "3.9" and python_version >= "3.8") and extra == "tests-strict"
Requires-Dist: coverage==6.1.1; (python_version < "3.8" and python_version >= "3.7") and extra == "tests-strict"
Requires-Dist: coverage==6.1.1; (python_version < "3.7" and python_version >= "3.6") and extra == "tests-strict"
Provides-Extra: optional-strict
Requires-Dist: textual==0.1.18; python_version >= "3.7" and extra == "optional-strict"
Requires-Dist: pint==0.24.4; (python_version < "4.0" and python_version >= "3.13") and extra == "optional-strict"
Requires-Dist: pint==0.23; (python_version < "3.13" and python_version >= "3.12") and extra == "optional-strict"
Requires-Dist: pint==0.18; (python_version < "3.12" and python_version >= "3.11") and extra == "optional-strict"
Requires-Dist: pint==0.18; (python_version < "3.11" and python_version >= "3.10") and extra == "optional-strict"
Requires-Dist: pint==0.18; (python_version < "3.10" and python_version >= "3.9") and extra == "optional-strict"
Requires-Dist: pint==0.18; (python_version < "3.9" and python_version >= "3.8") and extra == "optional-strict"
Provides-Extra: docs-strict
Requires-Dist: sphinx==5.0.1; extra == "docs-strict"
Requires-Dist: sphinx-autobuild==2021.3.14; extra == "docs-strict"
Requires-Dist: sphinx_rtd_theme==1.0.0; extra == "docs-strict"
Requires-Dist: sphinxcontrib-napoleon==0.7; extra == "docs-strict"
Requires-Dist: sphinx-autoapi==1.8.4; extra == "docs-strict"
Requires-Dist: Pygments==2.9.0; extra == "docs-strict"
Requires-Dist: myst_parser==0.18.0; extra == "docs-strict"
Requires-Dist: sphinx-reredirects==0.0.1; extra == "docs-strict"
Provides-Extra: linting-strict
Requires-Dist: flake8==5.0.0; extra == "linting-strict"
Dynamic: author
Dynamic: author-email
Dynamic: classifier
Dynamic: description
Dynamic: description-content-type
Dynamic: home-page
Dynamic: license
Dynamic: provides-extra
Dynamic: requires-dist
Dynamic: requires-python
Dynamic: summary
